hack4u/__init__.py
hack4u/courses.py
hack4u/utils.py
hack4u_project-1.0.2.dist-info/METADATA
hack4u_project-1.0.2.dist-info/WHEEL
hack4u_project-1.0.2.dist-info/top_level.txt
hack4u_project-1.0.2.dist-info/RECORD
