Metadata-Version: 2.4
Name: hack4u_project
Version: 1.0.2
Summary: Una biblioteca para consultar cursos de Hack4u.
Home-page: https://hack4u.io
Author: Sn0wBaall
Dynamic: author
Dynamic: description
Dynamic: description-content-type
Dynamic: home-page
Dynamic: summary
